{
    "Tags": [],
    "entities": {},
    "Canvases": [
        {
            "ID": 5116781668221841245,
            "Canvas Name": "New Canvas",
            "IsActive": true,
            "Sort Layer": 0,
            "Offset": {
                "x": 0.0,
                "y": 0.0,
                "z": 0.0
            },
            "UI Elements": [
                {
                    "ID": 17906803081632546541,
                    "Type Name": "UISlider",
                    "Sort Layer": 0,
                    "Horizontal Alignment": "middle",
                    "Vertical Alignment": "middle",
                    "Position": {
                        "x": 0.5,
                        "y": 0.5,
                        "z": 0.5
                    },
                    "Scale": {
                        "x": 0.5,
                        "y": 0.05000000074505806,
                        "z": 0.0
                    },
                    "Flags": 1,
                    "Name": "New Slider",
                    "UIScripts": {
                        "UIScripts": [],
                        "UIScripts Data": []
                    },
                    "Brightness": 1.0,
                    "color": {
                        "x": 0.0,
                        "y": 0.0,
                        "z": 0.0,
                        "w": 1.0
                    },
                    "Opacity": 1.0,
                    "RGBintensity": {
                        "x": 1.0,
                        "y": 1.0,
                        "z": 1.0,
                        "w": 1.0
                    },
                    "Textures": [
                        {
                            "m_id": 10267887709755569005
                        },
                        {
                            "m_id": 10267887709755569005
                        },
                        {
                            "m_id": 10267887709755569005
                        },
                        {
                            "m_id": 10267887709755569005
                        }
                    ],
                    "AudioQues": [
                        {
                            "m_id": 0
                        },
                        {
                            "m_id": 0
                        }
                    ],
                    "AudioQue Volume": 1.0,
                    "AudioQue Pitch": 1.0,
                    "AudioQue Priority": 128,
                    "SliderKnob Scale": {
                        "x": 0.019999999552965164,
                        "y": 0.07000000029802322,
                        "z": 0.0
                    },
                    "Percentage": 1.0,
                    "SliderBarBackgroundTexture": {
                        "m_id": 17197716863404279269
                    },
                    "SliderBarForegroundTexture": {
                        "m_id": 5602551787267187971
                    }
                }
            ]
        }
    ],
    "Global Illumination setting": {
        "x": 1.0,
        "y": 1.0,
        "z": 1.0,
        "intentsity": 0.019999999552965164
    }
}